pynetest/__init__.py
pynetest/__main__.py
pynetest/cli.py
pynetest/expectations.py
pynetest/matchers.py
pynetest/pyne_config.py
pynetest/pyne_pdb.py
pynetest/pyne_test_collector.py
pynetest/pyne_test_runner.py
pynetest/pyne_tester.py
pynetest/lib/__init__.py
pynetest/lib/expectation.py
pynetest/lib/matcher.py
pynetest/lib/message_format_helper.py
pynetest/lib/pyne_test_blocks.py
pynetest/lib/expectations/__init__.py
pynetest/lib/expectations/raise_expectation.py
pynetest/lib/expectations/raise_message_expectation.py
pynetest/lib/expectations/raise_type_expectation.py
pynetest/lib/expectations/to_be_between_expectation.py
pynetest/lib/matchers/__init__.py
pynetest/lib/matchers/has_length_matcher.py
pynetest/lib/matchers/matches_dict_matcher.py
pynetest/lib/matchers/matches_list_matcher.py
pynetest/lib/matchers/was_called_matcher.py
pynetest/lib/matchers/was_called_with_matcher.py
pynetest/lib/result_reporters/__init__.py
pynetest/lib/result_reporters/printing_reporter.py
pynetest/lib/result_reporters/pyne_result_reporters.py
pynetest/lib/result_reporters/record_for_summary_reporter.py
pynetest/test_doubles/__init__.py
pynetest/test_doubles/attached_spy.py
pynetest/test_doubles/sandbox.py
pynetest/test_doubles/spy.py
pynetest/test_doubles/stub.py
pynetest/test_doubles/test_double_expectations.py
pynetest/test_doubles/test_double_matchers.py
pynetest-0.2.22.dist-info/METADATA
pynetest-0.2.22.dist-info/WHEEL
pynetest-0.2.22.dist-info/entry_points.txt
pynetest-0.2.22.dist-info/licenses/LICENSE
pynetest-0.2.22.dist-info/RECORD
