Metadata-Version: 2.4
Name: pynetest
Version: 0.2.22
License-Expression: MIT
License-File: LICENSE
Requires-Python: >=3.8
